Metadata-Version: 1.1
Name: collective.notices
Version: 1.2
Summary: Adds Site-Wide Notification/Status Messages for Plone CMS
Home-page: https://github.com/softformance/collective.notices
Author: SoftFormance
Author-email: contact@softformance.com
License: gpl
Keywords: plone notification notice messages status
Platform: UNKNOWN
Classifier: Programming Language :: Python
Classifier: Programming Language :: Python :: 2.7
Classifier: Framework :: Plone
Classifier: Framework :: Plone :: 4.3
